{"retornoCalculo":{"valores":{"RET":"vrs=20171204","soccttfunassmenprm":"9,33","socifpdcobmenprm":"74,64","vlr1a_71_12":"1158,83","vlr1a_52_12":"1158,83","cstapl_71_12":"0,00","juros_52_12":"0,00","socflhcgtdoecobmenprm":"19,24","funvidtot":"25,00","iof_52_12":"0,38","socflhcgtdoetxa":"0,0000769580","soccttfunasssegtotcap":"5000,00","iof_71_12":"0,38","encargos_53_12":"0,00","socifpdtxa":"0,0000746381","socbascobsegtotcap":"1000000,00","juros_71_12":"0,00","cstapl_51_12":"0,00","funflhcgtdoecobmenprm":"13,47","vlrdemais_53_12":"1158,83","soccjgtxa":"0,0002239143","socipacobmenprm":"22,31","socflhcgtdoecobsegtotcap":"250000,00","glbcapprdvidtot":"30,00","socbastxa":"0,0003731905","socipatxa":"0,0000223066","mentotprm":"1158,83","funbascobsegtotcap":"700000,00","vlr1a_51_12":"1158,83","juros_53_12":"0,00","parcela_51_12":"12","socflh25txa":"0,0001896066","iof_51_12":"0,38","nome_71_12":"12X - 1º a Vista demais Carne","funifpdtxa":"0,0000746381","nome_53_12":"12X - 1ª A vista demais Debito C.corrente","funcjgcobmenprm":"78,37","funcjgtxa":"0,0002239143","functtfunassmenprm":"46,65","funflhcgtdoecobsegtotcap":"175000,00","cstapl_52_12":"0,00","encargos_52_12":"0,00","vlrdemais_52_12":"1158,83","fp_53_12":"53","vlrdemais_71_12":"1158,83","funanltotprm":"6009,12","anltotprm":"13905,96","soccjgcobsegtotcap":"500000,00","parcela_52_12":"12","parcela_71_12":"12","funbascobmenprm":"261,23","funper25flhcobmenprm":"33,18","funifpdcobmenprm":"52,25","socipacobsegtotcap":"1000000,00","funflhcgtdoetxa":"0,0000769580","nome_52_12":"12X - Debito C. Corrente","funfunasstxa":"0,0003731905","socvidtot":"5,00","funflh25txa":"0,0001896066","cstapl_53_12":"0,00","encargos_51_12":"0,00","socanltotprm":"7896,84","libshr":"4p11320171204_1.so","crg":"0,37500","socfunasstxa":"0,0003731905","funper25flhcobsegtotcap":"175000,00","fp_71_12":"71","fp_52_12":"52","parcela_53_12":"12","funmentotprm":"500,76","funipatxa":"0,0000223066","funipacobsegtotcap":"700000,00","funipacobmenprm":"15,61","soccjgcobmenprm":"111,96","vlrdemais_51_12":"1158,83","socmentotprm":"658,07","encargos_71_12":"0,00","funbastxa":"0,0003731905","iof_53_12":"0,38","funifpdcobsegtotcap":"700000,00","nome_51_12":"12X - 1ª Debito C.corrente demais Carne","socbascobmenprm":"373,19","funcjgcobsegtotcap":"350000,00","socper25flhcobsegtotcap":"250000,00","socifpdcobsegtotcap":"1000000,00","socper25flhcobmenprm":"47,40","juros_51_12":"0,00","vlr1a_53_12":"1158,83","functtfunasssegtotcap":"5000,00","fp_51_12":"51"},"mensagem":"Cálculo Efetuado"}}